kiwitcms_junit_xml_plugin-15.0.data/scripts/tcms-junit.xml-plugin
kiwitcms_junit_xml_plugin-15.0.dist-info/licenses/LICENSE
tcms_junit_plugin/__init__.py
tcms_junit_plugin/version.py
kiwitcms_junit_xml_plugin-15.0.dist-info/METADATA
kiwitcms_junit_xml_plugin-15.0.dist-info/WHEEL
kiwitcms_junit_xml_plugin-15.0.dist-info/top_level.txt
kiwitcms_junit_xml_plugin-15.0.dist-info/RECORD
