Metadata-Version: 2.4
Name: kiwitcms-junit.xml-plugin
Version: 15.0
Summary: junit.xml plugin for Kiwi TCMS test case management system
Home-page: https://github.com/kiwitcms/junit.xml-plugin
Author: Kiwi TCMS
Author-email: info@kiwitcms.org
License: GPLv3+
Classifier: Development Status :: 4 - Beta
Classifier: Environment :: Console
Classifier: Intended Audience :: Developers
Classifier: Intended Audience :: System Administrators
Classifier: License :: OSI Approved :: GNU General Public License v3 or later (GPLv3+)
Classifier: Operating System :: POSIX
Classifier: Programming Language :: Python
Classifier: Programming Language :: Python :: 3.9
Classifier: Programming Language :: Python :: 3.10
Classifier: Programming Language :: Python :: 3.11
Classifier: Topic :: Software Development
Classifier: Topic :: Software Development :: Libraries :: Python Modules
Classifier: Topic :: Software Development :: Quality Assurance
Classifier: Topic :: Software Development :: Testing
License-File: LICENSE
Requires-Dist: junitparser==3.2.0
Requires-Dist: tcms-api>=12.8.1
Requires-Dist: requests>=2.32.0
Dynamic: author
Dynamic: author-email
Dynamic: classifier
Dynamic: description
Dynamic: home-page
Dynamic: license
Dynamic: license-file
Dynamic: requires-dist
Dynamic: summary
